jnitrace/__init__.py
jnitrace/jnitrace.py
jnitrace/build/__init__.py
jnitrace/build/jnitrace.js
jnitrace-1.3.0.dist-info/LICENSE
jnitrace-1.3.0.dist-info/METADATA
jnitrace-1.3.0.dist-info/WHEEL
jnitrace-1.3.0.dist-info/entry_points.txt
jnitrace-1.3.0.dist-info/top_level.txt
jnitrace-1.3.0.dist-info/RECORD
