Metadata-Version: 2.1
Name: jnitrace
Version: 1.3.0
Summary: A tool for tracing use of the JNI in Android apps
Home-page: https://github.com/chame1eon/jnitrace
Author: chame1eon
License: UNKNOWN
Project-URL: Bug Reports, https://github.com/chame1eon/jnitrace/issues
Keywords: frida jni sre android tracing
Platform: UNKNOWN
Classifier: Development Status :: 5 - Production/Stable
Classifier: Intended Audience :: Developers
Classifier: Topic :: Software Development :: Debuggers
Classifier: License :: OSI Approved :: MIT License
Classifier: Programming Language :: Python :: 3
Classifier: Programming Language :: Python :: 3.4
Classifier: Programming Language :: Python :: 3.5
Classifier: Programming Language :: Python :: 3.6
Classifier: Programming Language :: Python :: 3.7
Requires-Python: >=3.0, <4
Requires-Dist: frida (>=10.0.0)
Requires-Dist: colorama
Requires-Dist: hexdump
